paramtools/__init__.py
paramtools/exceptions.py
paramtools/parameters.py
paramtools/schema.py
paramtools/schema_factory.py
paramtools/select.py
paramtools/sorted_key_list.py
paramtools/typing.py
paramtools/utils.py
paramtools/values.py
paramtools/contrib/__init__.py
paramtools/contrib/fields.py
paramtools/contrib/validate.py
paramtools/examples/taxparams-demo/defaults.json
paramtools/tests/__init__.py
paramtools/tests/test_fields.py
paramtools/tests/test_parameters.py
paramtools/tests/test_schema.py
paramtools/tests/test_select.py
paramtools/tests/test_sorted_key_list.py
paramtools/tests/test_utils.py
paramtools/tests/test_validate.py
paramtools/tests/test_values.py
paramtools/tests/test_examples/__init__.py
paramtools/tests/test_examples/test_baseball.py
paramtools/tests/test_examples/test_behresp.py
paramtools/tests/test_examples/test_tc_ex.py
paramtools-0.20.0.dist-info/licenses/LICENSE.txt
paramtools-0.20.0.dist-info/METADATA
paramtools-0.20.0.dist-info/WHEEL
paramtools-0.20.0.dist-info/top_level.txt
paramtools-0.20.0.dist-info/RECORD
