Metadata-Version: 2.4
Name: paramtools
Version: 0.20.0
Summary: Library for parameter processing and validation with a focus on computational modeling projects
Home-page: https://github.com/hdoupe/ParamTools
Author: Hank Doupe
Author-email: henrymdoupe@gmail.com
Classifier: Programming Language :: Python :: 3
Classifier: License :: OSI Approved :: MIT License
Classifier: Operating System :: OS Independent
License-File: LICENSE.txt
Requires-Dist: marshmallow>=4.0.0
Requires-Dist: numpy
Requires-Dist: python-dateutil>=2.8.0
Requires-Dist: fsspec
Requires-Dist: sortedcontainers
Dynamic: author
Dynamic: author-email
Dynamic: classifier
Dynamic: description
Dynamic: description-content-type
Dynamic: home-page
Dynamic: license-file
Dynamic: requires-dist
Dynamic: summary
